{
    "dialog": {
        "about": {
            "dependencies": {
                "column": {
                    "license": "License",
                    "name": "Dependency",
                    "url": "Website",
                    "version": "Version"
                }
            },
            "name": "pcxdbg",
            "version": {
                "application": {
                    "label": "Version {{version}}"
                },
                "build": {
                    "label": "Built on {{buildDate}}"
                },
                "electron": {
                    "label": "Electron: {{versionElectron}} (Chrome {{versionChrome}})"
                },
                "node": {
                    "label": "Node: {{versionNode}} (V8 {{versionV8}}, OpenSSL {{versionOpenSSL}})"
                },
                "revision": {
                    "label": "Revision #{{revisionNumber}} ({{revisionId}})"
                }
            }
        },
        "control": {
            "cancel": "Cancel",
            "close": "Close",
            "save": "Save"
        }
    },
    "host-explorer": {
        "title": "Host Explorer"
    },
    "main-menu": {
        "debug": {
            "break-all": "Break All",
            "continue": "Continue",
            "delete-all-breakpoints": "Delete All Breakpoints",
            "detach-all": "Detach All",
            "label": "&Debug",
            "new-breakpoint": {
                "data": "Data Breakpoint...",
                "function": "Function Breakpoint...",
                "label": "New Breakpoint"
            },
            "restart": "Restart",
            "step-into": "Step Into",
            "step-out": "Step Out",
            "step-over": "Step Over",
            "stop": "Stop Debugging",
            "terminate-all": "Terminate All",
            "toggle-breakpoint": "Toggle Breakpoint",
            "windows": {
                "autos": "Autos",
                "breakpoints": "Breakpoints",
                "call-stack": "Call Stack",
                "disassembly": "Disassembly",
                "immediates": "Immediates",
                "label": "Windows",
                "locals": "Locals",
                "memory": "Memory",
                "modules": "Modules",
                "output": "Output",
                "processes": "Processes",
                "registers": "Registers",
                "threads": "Threads",
                "watches": "Watches"
            }
       },
        "edit": {
            "copy": "Copy",
            "cut": "Cut",
            "delete": "Delete",
            "label": "&Edit",
            "paste": "Paste",
            "redo": "Redo",
            "select-all": "Select All",
            "undo": "Undo"
        },
        "file": {
            "close": "&Close",
            "close-connection": "Close Connection",
            "exit": "E&xit",
            "label": "&File",
            "open": {
                "connection": "&Connection...",
                "file": "&File...",
                "label": "&Open"
            },
            "page-setup": "Page Set&up...",
            "print": "&Print...",
            "recent-connections": "Recent Co&nnections",
            "recent-files": "Recent &Files",
            "save": "&Save <fileName>",
            "save-as": "Save <fileName> &As...",
            "save-all": "Save A&ll",
            "source-control": {
                "label": "Sou&rce Control"
            }
        },
        "help": {
            "about": "About pcxdbg",
            "feedback": {
                "label": "Send Feedback",
                "report-bug": "Report a Problem..."
            },
            "label": "&Help",
            "view": "View Help"
        },
        "profile": {
            "logout": "Sign Out",
            "preferences": "Preferences",
            "rights": "Rights"
        },
        "tools": {
            "customize": "Customize",
            "label": "&Tools",
            "options": "Options"
        },
        "view": {
            "bookmark-window": "Bookmark Window",
            "call-hierarchy": "Call Hierarchy",
            "chat": "Chat",
            "command-window": "Command Window",
            "error-list": "Error List",
            "fullscreen": "Full Screen",
            "host-explorer": "Host Explorer",
            "label": "&View",
            "navigate-backward": "Navigate Backward",
            "navigate-forward": "Navigate Forward",
            "network-explorer": "Network Explorer",
            "notifications": "Notifications",
            "object-browser": "Object Browser",
            "output": "Output",
            "toolbars": {
                "label": "Toolbars"
            }
        },
        "window": {
            "apply-window-layout": {
                "label": "Appl&y Window Layout",
                "none-saved": "No Saved Layouts"
            },
            "auto-hide": "&Auto Hide",
            "auto-hide-all": "A&uto Hide All",
            "close-all-documents": "C&lose All Documents",
            "dock": "Doc&k",
            "float": "&Float",
            "hide": "&Hide",
            "label": "&Window",
            "manage-window-layouts": "&Manage Window Layouts",
            "new-window": "&New Window",
            "pin-tab": "&Pin Tab",
            "reset-window-layout": "&Reset Winow Layout",
            "save-window-layout": "&Save Window Layout",
            "split": "S&plit",
            "windows": "&Windows..."
        }
    },
    "network-explorer": {
        "title": "Network Explorer"
    },
    "quick-launch": {
        "placeholder": "Quick Launch (Ctrl+Q)",
        "search": "Search",
        "title": "Type words to search for or type \"@\" to list the available search providers"
    },
    "status-bar": {
        "background-tasks": "Background tasks"
    },
    "title-bar": {
        "controls": {
            "close": "Close",
            "maximize": "Maximize",
            "minimize": "Minimize",
            "restore": "Restore"
        },
        "label": "pcxdbg"
    }
}